[
  {
    "name": "c1",
    "properties": [
      "a",
      "b",
      "c",
      "d"
    ],
    "items": [
      {
        "a": "sdfAAA",
        "b": "fsdfsdAAAAA",
        "c": "fsdfsdAAA",
        "d": "fsdsfdAAA",
        "id": 1
      },
      {
        "a": "zedAAA",
        "b": "zerezezrAAAAAAAAAAAAAAAAAAAAAAAAAA",
        "c": "rezrze",
        "d": "rezreezr",
        "id": 2
      },
      {
        "a": "dffdfd",
        "b": "fdfdsdf",
        "c": "ffdfddfsdfs",
        "d": "fdfddfdfs",
        "id": 3
      }
    ],
    "lastitemid": 3
  },
  {
    "name": "c3",
    "properties": [
      "p",
      "q"
    ],
    "items": [
      {
        "p": "dfdfds",
        "q": "fdfdsfds",
        "id": 1
      }
    ],
    "lastitemid": 1
  },
  {
    "name": "famille",
    "properties": [
      "membres",
      "age"
    ],
    "items": [
      {
        "membres": "Antoine",
        "age": "5",
        "id": 1
      },
      {
        "membres": "Mélanie",
        "age": "32",
        "id": 2
      }
    ],
    "lastitemid": 2
  },
  {
    "name": "livre",
    "properties": [
      "auteur",
      "titre",
      "commentaire"
    ],
    "items": [
      {
        "auteur": "Stendhal",
        "titre": "Le Rouge et le Noir",
        "commentaire": "Très bon livre",
        "id": 1
      }
    ],
    "lastitemid": 1
  },
  {
    "name": "postes",
    "shortProperties": [
      "date",
      "duree"
    ],
    "longProperties": [
      "commenaire",
      "missions"
    ],
    "items": [],
    "lastitemid": 0
  }
]